contactform/__init__.py
contactform/admin.py
contactform/apps.py
contactform/forms.py
contactform/models.py
contactform/tests.py
contactform/urls.py
contactform/views.py
contactform/migrations/0001_initial.py
contactform/migrations/__init__.py
contactform/migrations/__pycache__/0001_initial.cpython-310.pyc
contactform/migrations/__pycache__/0001_initial.cpython-312.pyc
contactform/migrations/__pycache__/__init__.cpython-310.pyc
contactform/migrations/__pycache__/__init__.cpython-312.pyc
contactform/templates/form.html
orfrom-0.1.0.dist-info/LICENSE
orfrom-0.1.0.dist-info/METADATA
orfrom-0.1.0.dist-info/WHEEL
orfrom-0.1.0.dist-info/top_level.txt
orfrom-0.1.0.dist-info/RECORD
