Metadata-Version: 2.1
Name: orfrom
Version: 0.1.0
Summary: Application Django réutilisable : formulaire de contact
Home-page: UNKNOWN
Author: Ton Nom
Author-email: ton@email.com
License: MIT
Platform: UNKNOWN
Classifier: Development Status :: 3 - Alpha
Classifier: Framework :: Django
Classifier: Framework :: Django :: 3.2
Classifier: License :: OSI Approved :: MIT License
Classifier: Programming Language :: Python :: 3
Classifier: Operating System :: OS Independent
Requires-Python: >=3.6
License-File: LICENSE
Requires-Dist: django>=3.2
